industrial_readers_client/__init__.py
industrial_readers_client/client.py
industrial_readers_client-1.0.1.dist-info/METADATA
industrial_readers_client-1.0.1.dist-info/WHEEL
industrial_readers_client-1.0.1.dist-info/top_level.txt
industrial_readers_client-1.0.1.dist-info/RECORD
