Metadata-Version: 2.4
Name: industrial-readers-client
Version: 1.0.1
Summary: High-performance Python client for Industrial Readers Server
Home-page: https://gitlab.com/soberonlineemail/profilereaders
Author: Industrial Readers Team
Author-email: Industrial Readers Team <contact@example.com>
License: MIT
Project-URL: Homepage, https://gitlab.com/soberonlineemail/profilereaders
Project-URL: Repository, https://gitlab.com/soberonlineemail/profilereaders
Project-URL: Issues, https://gitlab.com/soberonlineemail/profilereaders/-/issues
Keywords: document,reader,excel,word,pdf,powerpoint,file,parsing
Classifier: Development Status :: 5 - Production/Stable
Classifier: Intended Audience :: Developers
Classifier: License :: OSI Approved :: MIT License
Classifier: Operating System :: OS Independent
Classifier: Programming Language :: Python :: 3
Classifier: Programming Language :: Python :: 3.8
Classifier: Programming Language :: Python :: 3.9
Classifier: Programming Language :: Python :: 3.10
Classifier: Programming Language :: Python :: 3.11
Classifier: Programming Language :: Python :: 3.12
Requires-Python: >=3.8
Requires-Dist: requests>=2.25.0
Provides-Extra: dev
Requires-Dist: pytest>=6.0; extra == "dev"
Requires-Dist: black; extra == "dev"
Requires-Dist: flake8; extra == "dev"
Dynamic: author
Dynamic: home-page
Dynamic: requires-python
